<?xml version="1.0" encoding="utf-8"?>
<root>
  <ManageSoft connectiontype="ecm" runintransaction="False" />
  <Imports>
    <Import Type="Excel" Name="UQCorpUnits" Template="" Enabled="False" 
    	ConnectionString="Provider=Microsoft.ACE.OLEDB.12.0;Data Source=UQCorpUnits.xlsx;Extended Properties='Excel 12.0 Xml;HDR=Yes;IMEX=0'" 
    	Query="select * from [Sheet$]"
      >
      <Object Type="CorporateUnit" Name="Corporate Unit" Update="True" Create="True" OutputField="CorporateUnit_ID">
        <Property Type="groupcn" Name="Name" Update="Never" ValueType="Field Value" Value="Path" UseForMatching="True" Length="128" RegexSplit="/" />
        <Property Type="groupexid" Name="ID" Update="Never" ValueType="Field Value" Value="CorporateUnit_ID" UseForMatching="True" MatchingMode="like" DataType="Integer" UseNullValueForMatching="RemoveProperty" />
        <Property Type="comments" Name="Description" Update="Do not blank" ValueType="Field Value" Value="Description" />
      </Object>
    </Import>
  </Imports>
</root>